MANIFEST.in
requirements.txt
setup.cfg
setup.py
dhcp_relay/__init__.py
dhcp_relay/commons.py
dhcp_relay/defaults.py
dhcp_relay/exceptions.py
dhcp_relay/globals.py
dhcp_relay/listener.py
dhcp_relay/pkt_crafter.py
dhcp_relay/relay.py
dhcp_relay/util.py
dhcp_relay.egg-info/PKG-INFO
dhcp_relay.egg-info/SOURCES.txt
dhcp_relay.egg-info/dependency_links.txt
dhcp_relay.egg-info/requires.txt
dhcp_relay.egg-info/top_level.txt